{
  "Sales Order": {
    "module": "Selling",
    "description": "Standard ERPNext doctype for Sales Order",
    "fields": [
      "title (Data)",
      "naming_series (Select)",
      "customer (Link)",
      "customer_name (Data)",
      "tax_id (Data)",
      "order_type (Select)",
      "transaction_date (Date)",
      "delivery_date (Date)",
      "po_no (Data)",
      "po_date (Date)",
      "company (Link)",
      "skip_delivery_note (Check)",
      "amended_from (Link)",
      "cost_center (Link)",
      "project (Link)",
      "currency (Link)",
      "conversion_rate (Float)",
      "selling_price_list (Link)",
      "price_list_currency (Link)",
      "plc_conversion_rate (Float)",
      "ignore_pricing_rule (Check)",
      "scan_barcode (Data)",
      "set_warehouse (Link)",
      "reserve_stock (Check)",
      "items (Table)",
      "total_qty (Float)",
      "total_net_weight (Float)",
      "base_total (Currency)",
      "base_net_total (Currency)",
      "total (Currency)",
      "net_total (Currency)",
      "tax_category (Link)",
      "taxes_and_charges (Link)",
      "shipping_rule (Link)",
      "incoterm (Link)",
      "named_place (Data)",
      "taxes (Table)",
      "base_total_taxes_and_charges (Currency)",
      "total_taxes_and_charges (Currency)",
      "base_grand_total (Currency)",
      "base_rounding_adjustment (Currency)",
      "base_rounded_total (Currency)",
      "base_in_words (Data)",
      "grand_total (Currency)",
      "rounding_adjustment (Currency)",
      "rounded_total (Currency)",
      "in_words (Data)",
      "advance_paid (Currency)",
      "disable_rounded_total (Check)",
      "apply_discount_on (Select)",
      "base_discount_amount (Currency)",
      "coupon_code (Link)",
      "additional_discount_percentage (Float)",
      "discount_amount (Currency)",
      "other_charges_calculation (Text Editor)",
      "packed_items (Table)",
      "pricing_rules (Table)",
      "customer_address (Link)",
      "address_display (Small Text)",
      "customer_group (Link)",
      "territory (Link)",
      "contact_person (Link)",
      "contact_display (Small Text)",
      "contact_phone (Data)",
      "contact_mobile (Small Text)",
      "contact_email (Data)",
      "shipping_address_name (Link)",
      "shipping_address (Small Text)",
      "dispatch_address_name (Link)",
      "dispatch_address (Small Text)",
      "company_address (Link)",
      "company_address_display (Small Text)",
      "company_contact_person (Link)",
      "payment_terms_template (Link)",
      "payment_schedule (Table)",
      "tc_name (Link)",
      "terms (Text Editor)",
      "status (Select)",
      "delivery_status (Select)",
      "per_delivered (Percent)",
      "per_billed (Percent)",
      "per_picked (Percent)",
      "billing_status (Select)",
      "sales_partner (Link)",
      "amount_eligible_for_commission (Currency)",
      "commission_rate (Float)",
      "total_commission (Currency)",
      "sales_team (Table)",
      "loyalty_points (Int)",
      "loyalty_amount (Currency)",
      "from_date (Date)",
      "to_date (Date)",
      "auto_repeat (Link)",
      "update_auto_repeat_reference (Button)",
      "letter_head (Link)",
      "group_same_items (Check)",
      "select_print_heading (Link)",
      "language (Data)",
      "is_internal_customer (Check)",
      "represents_company (Link)",
      "source (Link)",
      "inter_company_order_reference (Link)",
      "campaign (Link)",
      "party_account_currency (Link)",
      "name (Data)",
      "creation (Datetime)",
      "modified (Datetime)",
      "owner (Link)",
      "modified_by (Link)",
      "docstatus (Int)",
      "idx (Int)"
    ]
  },
  "Sales Invoice": {
    "module": "Accounts",
    "description": "Standard ERPNext doctype for Sales Invoice",
    "fields": [
      "title (Data)",
      "naming_series (Select)",
      "customer (Link)",
      "customer_name (Small Text)",
      "tax_id (Data)",
      "company (Link)",
      "company_tax_id (Data)",
      "posting_date (Date)",
      "posting_time (Time)",
      "set_posting_time (Check)",
      "due_date (Date)",
      "is_pos (Check)",
      "pos_profile (Link)",
      "is_consolidated (Check)",
      "is_return (Check)",
      "return_against (Link)",
      "update_outstanding_for_self (Check)",
      "update_billed_amount_in_sales_order (Check)",
      "update_billed_amount_in_delivery_note (Check)",
      "is_debit_note (Check)",
      "amended_from (Link)",
      "cost_center (Link)",
      "project (Link)",
      "currency (Link)",
      "conversion_rate (Float)",
      "selling_price_list (Link)",
      "price_list_currency (Link)",
      "plc_conversion_rate (Float)",
      "ignore_pricing_rule (Check)",
      "scan_barcode (Data)",
      "update_stock (Check)",
      "set_warehouse (Link)",
      "set_target_warehouse (Link)",
      "items (Table)",
      "total_qty (Float)",
      "total_net_weight (Float)",
      "base_total (Currency)",
      "base_net_total (Currency)",
      "total (Currency)",
      "net_total (Currency)",
      "tax_category (Link)",
      "taxes_and_charges (Link)",
      "shipping_rule (Link)",
      "incoterm (Link)",
      "named_place (Data)",
      "taxes (Table)",
      "base_total_taxes_and_charges (Currency)",
      "total_taxes_and_charges (Currency)",
      "base_grand_total (Currency)",
      "base_rounding_adjustment (Currency)",
      "base_rounded_total (Currency)",
      "base_in_words (Small Text)",
      "grand_total (Currency)",
      "rounding_adjustment (Currency)",
      "use_company_roundoff_cost_center (Check)",
      "rounded_total (Currency)",
      "in_words (Small Text)",
      "total_advance (Currency)",
      "outstanding_amount (Currency)",
      "disable_rounded_total (Check)",
      "apply_discount_on (Select)",
      "base_discount_amount (Currency)",
      "is_cash_or_non_trade_discount (Check)",
      "additional_discount_account (Link)",
      "additional_discount_percentage (Float)",
      "discount_amount (Currency)",
      "other_charges_calculation (Text Editor)",
      "pricing_rules (Table)",
      "packed_items (Table)",
      "product_bundle_help (HTML)",
      "timesheets (Table)",
      "total_billing_hours (Float)",
      "total_billing_amount (Currency)",
      "cash_bank_account (Link)",
      "payments (Table)",
      "base_paid_amount (Currency)",
      "paid_amount (Currency)",
      "base_change_amount (Currency)",
      "change_amount (Currency)",
      "account_for_change_amount (Link)",
      "allocate_advances_automatically (Check)",
      "only_include_allocated_payments (Check)",
      "get_advances (Button)",
      "advances (Table)",
      "write_off_amount (Currency)",
      "base_write_off_amount (Currency)",
      "write_off_outstanding_amount_automatically (Check)",
      "write_off_account (Link)",
      "write_off_cost_center (Link)",
      "redeem_loyalty_points (Check)",
      "loyalty_points (Int)",
      "loyalty_amount (Currency)",
      "loyalty_program (Link)",
      "loyalty_redemption_account (Link)",
      "loyalty_redemption_cost_center (Link)",
      "customer_address (Link)",
      "address_display (Small Text)",
      "contact_person (Link)",
      "contact_display (Small Text)",
      "contact_mobile (Small Text)",
      "contact_email (Data)",
      "territory (Link)",
      "shipping_address_name (Link)",
      "shipping_address (Small Text)",
      "dispatch_address_name (Link)",
      "dispatch_address (Small Text)",
      "company_address (Link)",
      "company_address_display (Small Text)",
      "company_contact_person (Link)",
      "ignore_default_payment_terms_template (Check)",
      "payment_terms_template (Link)",
      "payment_schedule (Table)",
      "tc_name (Link)",
      "terms (Text Editor)",
      "po_no (Data)",
      "po_date (Date)",
      "debit_to (Link)",
      "party_account_currency (Link)",
      "is_opening (Select)",
      "unrealized_profit_loss_account (Link)",
      "against_income_account (Small Text)",
      "sales_partner (Link)",
      "amount_eligible_for_commission (Currency)",
      "commission_rate (Float)",
      "total_commission (Currency)",
      "sales_team (Table)",
      "letter_head (Link)",
      "group_same_items (Check)",
      "select_print_heading (Link)",
      "language (Data)",
      "subscription (Link)",
      "from_date (Date)",
      "auto_repeat (Link)",
      "to_date (Date)",
      "update_auto_repeat_reference (Button)",
      "status (Select)",
      "inter_company_invoice_reference (Link)",
      "campaign (Link)",
      "represents_company (Link)",
      "source (Link)",
      "customer_group (Link)",
      "is_internal_customer (Check)",
      "is_discounted (Check)",
      "remarks (Small Text)",
      "name (Data)",
      "creation (Datetime)",
      "modified (Datetime)",
      "owner (Link)",
      "modified_by (Link)",
      "docstatus (Int)",
      "idx (Int)"
    ]
  },
  "Quotation": {
    "module": "Selling",
    "description": "Standard ERPNext doctype for Quotation",
    "fields": [
      "title (Data)",
      "naming_series (Select)",
      "quotation_to (Link)",
      "party_name (Dynamic Link)",
      "customer_name (Data)",
      "transaction_date (Date)",
      "valid_till (Date)",
      "order_type (Select)",
      "company (Link)",
      "amended_from (Link)",
      "currency (Link)",
      "conversion_rate (Float)",
      "selling_price_list (Link)",
      "price_list_currency (Link)",
      "plc_conversion_rate (Float)",
      "ignore_pricing_rule (Check)",
      "scan_barcode (Data)",
      "items (Table)",
      "total_qty (Float)",
      "total_net_weight (Float)",
      "base_total (Currency)",
      "base_net_total (Currency)",
      "total (Currency)",
      "net_total (Currency)",
      "tax_category (Link)",
      "taxes_and_charges (Link)",
      "shipping_rule (Link)",
      "incoterm (Link)",
      "named_place (Data)",
      "taxes (Table)",
      "base_total_taxes_and_charges (Currency)",
      "total_taxes_and_charges (Currency)",
      "base_grand_total (Currency)",
      "base_rounding_adjustment (Currency)",
      "base_rounded_total (Currency)",
      "base_in_words (Data)",
      "grand_total (Currency)",
      "rounding_adjustment (Currency)",
      "rounded_total (Currency)",
      "disable_rounded_total (Check)",
      "in_words (Data)",
      "apply_discount_on (Select)",
      "base_discount_amount (Currency)",
      "coupon_code (Link)",
      "additional_discount_percentage (Float)",
      "discount_amount (Currency)",
      "referral_sales_partner (Link)",
      "other_charges_calculation (Text Editor)",
      "packed_items (Table)",
      "pricing_rules (Table)",
      "customer_address (Link)",
      "address_display (Small Text)",
      "contact_person (Link)",
      "contact_display (Small Text)",
      "contact_mobile (Small Text)",
      "contact_email (Data)",
      "shipping_address_name (Link)",
      "shipping_address (Small Text)",
      "company_address (Link)",
      "company_address_display (Small Text)",
      "company_contact_person (Link)",
      "payment_terms_template (Link)",
      "payment_schedule (Table)",
      "tc_name (Link)",
      "terms (Text Editor)",
      "auto_repeat (Link)",
      "update_auto_repeat_reference (Button)",
      "letter_head (Link)",
      "group_same_items (Check)",
      "select_print_heading (Link)",
      "language (Data)",
      "lost_reasons (Table MultiSelect)",
      "competitors (Table MultiSelect)",
      "order_lost_reason (Small Text)",
      "status (Select)",
      "customer_group (Link)",
      "territory (Link)",
      "campaign (Link)",
      "source (Link)",
      "opportunity (Link)",
      "supplier_quotation (Link)",
      "enq_det (Text)",
      "name (Data)",
      "creation (Datetime)",
      "modified (Datetime)",
      "owner (Link)",
      "modified_by (Link)",
      "docstatus (Int)",
      "idx (Int)"
    ]
  },
  "Delivery Note": {
    "module": "Stock",
    "description": "Standard ERPNext doctype for Delivery Note",
    "fields": [
      "title (Data)",
      "naming_series (Select)",
      "customer (Link)",
      "tax_id (Data)",
      "customer_name (Data)",
      "posting_date (Date)",
      "posting_time (Time)",
      "set_posting_time (Check)",
      "company (Link)",
      "amended_from (Link)",
      "is_return (Check)",
      "issue_credit_note (Check)",
      "return_against (Link)",
      "cost_center (Link)",
      "project (Link)",
      "currency (Link)",
      "conversion_rate (Float)",
      "selling_price_list (Link)",
      "price_list_currency (Link)",
      "plc_conversion_rate (Float)",
      "ignore_pricing_rule (Check)",
      "scan_barcode (Data)",
      "pick_list (Link)",
      "set_warehouse (Link)",
      "set_target_warehouse (Link)",
      "items (Table)",
      "total_qty (Float)",
      "total_net_weight (Float)",
      "base_total (Currency)",
      "base_net_total (Currency)",
      "total (Currency)",
      "net_total (Currency)",
      "tax_category (Link)",
      "taxes_and_charges (Link)",
      "shipping_rule (Link)",
      "incoterm (Link)",
      "named_place (Data)",
      "taxes (Table)",
      "base_total_taxes_and_charges (Currency)",
      "total_taxes_and_charges (Currency)",
      "base_grand_total (Currency)",
      "base_rounding_adjustment (Currency)",
      "base_rounded_total (Currency)",
      "base_in_words (Data)",
      "grand_total (Currency)",
      "rounding_adjustment (Currency)",
      "rounded_total (Currency)",
      "in_words (Data)",
      "disable_rounded_total (Check)",
      "apply_discount_on (Select)",
      "base_discount_amount (Currency)",
      "additional_discount_percentage (Float)",
      "discount_amount (Currency)",
      "other_charges_calculation (Text Editor)",
      "packed_items (Table)",
      "product_bundle_help (HTML)",
      "pricing_rules (Table)",
      "customer_address (Link)",
      "address_display (Small Text)",
      "contact_person (Link)",
      "contact_display (Small Text)",
      "contact_mobile (Small Text)",
      "contact_email (Data)",
      "shipping_address_name (Link)",
      "shipping_address (Small Text)",
      "dispatch_address_name (Link)",
      "dispatch_address (Small Text)",
      "company_address (Link)",
      "company_address_display (Small Text)",
      "company_contact_person (Link)",
      "tc_name (Link)",
      "terms (Text Editor)",
      "per_billed (Percent)",
      "status (Select)",
      "per_installed (Percent)",
      "installation_status (Select)",
      "per_returned (Percent)",
      "transporter (Link)",
      "driver (Link)",
      "lr_no (Data)",
      "vehicle_no (Data)",
      "transporter_name (Data)",
      "driver_name (Data)",
      "lr_date (Date)",
      "po_no (Small Text)",
      "po_date (Date)",
      "sales_partner (Link)",
      "amount_eligible_for_commission (Currency)",
      "commission_rate (Float)",
      "total_commission (Currency)",
      "sales_team (Table)",
      "auto_repeat (Link)",
      "letter_head (Link)",
      "print_without_amount (Check)",
      "group_same_items (Check)",
      "select_print_heading (Link)",
      "language (Data)",
      "is_internal_customer (Check)",
      "represents_company (Link)",
      "inter_company_reference (Link)",
      "customer_group (Link)",
      "territory (Link)",
      "source (Link)",
      "campaign (Link)",
      "excise_page (Data)",
      "instructions (Text)",
      "name (Data)",
      "creation (Datetime)",
      "modified (Datetime)",
      "owner (Link)",
      "modified_by (Link)",
      "docstatus (Int)",
      "idx (Int)"
    ]
  },
  "Customer": {
    "module": "Selling",
    "description": "Buyer of Goods and Services.",
    "fields": [
      "naming_series (Select)",
      "salutation (Link)",
      "customer_name (Data)",
      "customer_type (Select)",
      "customer_group (Link)",
      "territory (Link)",
      "gender (Link)",
      "lead_name (Link)",
      "opportunity_name (Link)",
      "prospect_name (Link)",
      "account_manager (Link)",
      "image (Attach Image)",
      "default_currency (Link)",
      "default_bank_account (Link)",
      "default_price_list (Link)",
      "is_internal_customer (Check)",
      "represents_company (Link)",
      "companies (Table)",
      "market_segment (Link)",
      "industry (Link)",
      "customer_pos_id (Data)",
      "website (Data)",
      "language (Link)",
      "customer_details (Text)",
      "address_html (HTML)",
      "contact_html (HTML)",
      "customer_primary_address (Link)",
      "primary_address (Text)",
      "customer_primary_contact (Link)",
      "mobile_no (Read Only)",
      "email_id (Read Only)",
      "tax_id (Data)",
      "tax_category (Link)",
      "tax_withholding_category (Link)",
      "payment_terms (Link)",
      "credit_limits (Table)",
      "accounts (Table)",
      "loyalty_program (Link)",
      "loyalty_program_tier (Data)",
      "sales_team (Table)",
      "default_sales_partner (Link)",
      "default_commission_rate (Float)",
      "so_required (Check)",
      "dn_required (Check)",
      "is_frozen (Check)",
      "disabled (Check)",
      "portal_users (Table)",
      "name (Data)",
      "creation (Datetime)",
      "modified (Datetime)",
      "owner (Link)",
      "modified_by (Link)",
      "docstatus (Int)",
      "idx (Int)"
    ]
  },
  "Sales Partner": {
    "module": "Setup",
    "description": "A third party distributor / dealer / commission agent / affiliate / reseller who sells the companies products for a commission.",
    "fields": [
      "partner_name (Data)",
      "partner_type (Link)",
      "territory (Link)",
      "commission_rate (Float)",
      "address_desc (HTML)",
      "address_html (HTML)",
      "contact_desc (HTML)",
      "contact_html (HTML)",
      "targets (Table)",
      "show_in_website (Check)",
      "referral_code (Data)",
      "route (Data)",
      "logo (Attach)",
      "partner_website (Data)",
      "introduction (Text)",
      "description (Text Editor)",
      "name (Data)",
      "creation (Datetime)",
      "modified (Datetime)",
      "owner (Link)",
      "modified_by (Link)",
      "docstatus (Int)",
      "idx (Int)"
    ]
  },
  "Item": {
    "module": "Stock",
    "description": "A Product or a Service that is bought, sold or kept in stock.",
    "fields": [
      "naming_series (Select)",
      "item_code (Data)",
      "item_name (Data)",
      "item_group (Link)",
      "stock_uom (Link)",
      "disabled (Check)",
      "allow_alternative_item (Check)",
      "is_stock_item (Check)",
      "has_variants (Check)",
      "opening_stock (Float)",
      "valuation_rate (Currency)",
      "standard_rate (Currency)",
      "is_fixed_asset (Check)",
      "auto_create_assets (Check)",
      "is_grouped_asset (Check)",
      "asset_category (Link)",
      "asset_naming_series (Select)",
      "over_delivery_receipt_allowance (Float)",
      "over_billing_allowance (Float)",
      "image (Attach Image)",
      "description (Text Editor)",
      "brand (Link)",
      "uoms (Table)",
      "shelf_life_in_days (Int)",
      "end_of_life (Date)",
      "default_material_request_type (Select)",
      "valuation_method (Select)",
      "warranty_period (Data)",
      "weight_per_unit (Float)",
      "weight_uom (Link)",
      "allow_negative_stock (Check)",
      "barcodes (Table)",
      "reorder_levels (Table)",
      "has_batch_no (Check)",
      "create_new_batch (Check)",
      "batch_number_series (Data)",
      "has_expiry_date (Check)",
      "retain_sample (Check)",
      "sample_quantity (Int)",
      "has_serial_no (Check)",
      "serial_no_series (Data)",
      "variant_of (Link)",
      "variant_based_on (Select)",
      "attributes (Table)",
      "enable_deferred_expense (Check)",
      "no_of_months_exp (Int)",
      "enable_deferred_revenue (Check)",
      "no_of_months (Int)",
      "item_defaults (Table)",
      "purchase_uom (Link)",
      "min_order_qty (Float)",
      "safety_stock (Float)",
      "is_purchase_item (Check)",
      "lead_time_days (Int)",
      "last_purchase_rate (Float)",
      "is_customer_provided_item (Check)",
      "customer (Link)",
      "delivered_by_supplier (Check)",
      "supplier_items (Table)",
      "country_of_origin (Link)",
      "customs_tariff_number (Link)",
      "sales_uom (Link)",
      "grant_commission (Check)",
      "is_sales_item (Check)",
      "max_discount (Float)",
      "customer_items (Table)",
      "taxes (Table)",
      "inspection_required_before_purchase (Check)",
      "quality_inspection_template (Link)",
      "inspection_required_before_delivery (Check)",
      "include_item_in_manufacturing (Check)",
      "is_sub_contracted_item (Check)",
      "default_bom (Link)",
      "customer_code (Small Text)",
      "default_item_manufacturer (Link)",
      "default_manufacturer_part_no (Data)",
      "total_projected_qty (Float)",
      "name (Data)",
      "creation (Datetime)",
      "modified (Datetime)",
      "owner (Link)",
      "modified_by (Link)",
      "docstatus (Int)",
      "idx (Int)"
    ]
  },
  "Warehouse": {
    "module": "Stock",
    "description": "A logical Warehouse against which stock entries are made.",
    "fields": [
      "disabled (Check)",
      "warehouse_name (Data)",
      "is_group (Check)",
      "parent_warehouse (Link)",
      "is_rejected_warehouse (Check)",
      "account (Link)",
      "company (Link)",
      "address_html (HTML)",
      "contact_html (HTML)",
      "email_id (Data)",
      "phone_no (Data)",
      "mobile_no (Data)",
      "address_line_1 (Data)",
      "address_line_2 (Data)",
      "city (Data)",
      "state (Data)",
      "pin (Data)",
      "warehouse_type (Link)",
      "default_in_transit_warehouse (Link)",
      "lft (Int)",
      "rgt (Int)",
      "old_parent (Link)",
      "name (Data)",
      "creation (Datetime)",
      "modified (Datetime)",
      "owner (Link)",
      "modified_by (Link)",
      "docstatus (Int)",
      "idx (Int)"
    ]
  },
  "Bin": {
    "module": "Stock",
    "description": "Standard ERPNext doctype for Bin",
    "fields": [
      "item_code (Link)",
      "warehouse (Link)",
      "actual_qty (Float)",
      "planned_qty (Float)",
      "indented_qty (Float)",
      "ordered_qty (Float)",
      "projected_qty (Float)",
      "reserved_qty (Float)",
      "reserved_qty_for_production (Float)",
      "reserved_qty_for_sub_contract (Float)",
      "reserved_qty_for_production_plan (Float)",
      "reserved_stock (Float)",
      "stock_uom (Link)",
      "valuation_rate (Float)",
      "stock_value (Float)",
      "name (Data)",
      "creation (Datetime)",
      "modified (Datetime)",
      "owner (Link)",
      "modified_by (Link)",
      "docstatus (Int)",
      "idx (Int)"
    ]
  },
  "Stock Entry": {
    "module": "Stock",
    "description": "Standard ERPNext doctype for Stock Entry",
    "fields": [
      "naming_series (Select)",
      "stock_entry_type (Link)",
      "outgoing_stock_entry (Link)",
      "purpose (Select)",
      "add_to_transit (Check)",
      "work_order (Link)",
      "purchase_order (Link)",
      "subcontracting_order (Link)",
      "delivery_note_no (Link)",
      "sales_invoice_no (Link)",
      "pick_list (Link)",
      "purchase_receipt_no (Link)",
      "asset_repair (Link)",
      "company (Link)",
      "posting_date (Date)",
      "posting_time (Time)",
      "set_posting_time (Check)",
      "inspection_required (Check)",
      "apply_putaway_rule (Check)",
      "from_bom (Check)",
      "use_multi_level_bom (Check)",
      "bom_no (Link)",
      "fg_completed_qty (Float)",
      "get_items (Button)",
      "process_loss_percentage (Percent)",
      "process_loss_qty (Float)",
      "from_warehouse (Link)",
      "source_warehouse_address (Link)",
      "source_address_display (Small Text)",
      "to_warehouse (Link)",
      "target_warehouse_address (Link)",
      "target_address_display (Small Text)",
      "scan_barcode (Data)",
      "items (Table)",
      "get_stock_and_rate (Button)",
      "total_outgoing_value (Currency)",
      "total_incoming_value (Currency)",
      "value_difference (Currency)",
      "additional_costs (Table)",
      "total_additional_costs (Currency)",
      "supplier (Link)",
      "supplier_name (Data)",
      "supplier_address (Link)",
      "address_display (Small Text)",
      "project (Link)",
      "select_print_heading (Link)",
      "letter_head (Link)",
      "is_opening (Select)",
      "remarks (Text)",
      "per_transferred (Percent)",
      "total_amount (Currency)",
      "job_card (Link)",
      "amended_from (Link)",
      "credit_note (Link)",
      "is_return (Check)",
      "name (Data)",
      "creation (Datetime)",
      "modified (Datetime)",
      "owner (Link)",
      "modified_by (Link)",
      "docstatus (Int)",
      "idx (Int)"
    ]
  },
  "Stock Ledger Entry": {
    "module": "Stock",
    "description": "Standard ERPNext doctype for Stock Ledger Entry",
    "fields": [
      "item_code (Link)",
      "warehouse (Link)",
      "posting_date (Date)",
      "posting_time (Time)",
      "posting_datetime (Datetime)",
      "is_adjustment_entry (Check)",
      "auto_created_serial_and_batch_bundle (Check)",
      "voucher_type (Link)",
      "voucher_no (Dynamic Link)",
      "voucher_detail_no (Data)",
      "serial_and_batch_bundle (Link)",
      "dependant_sle_voucher_detail_no (Data)",
      "recalculate_rate (Check)",
      "actual_qty (Float)",
      "qty_after_transaction (Float)",
      "incoming_rate (Currency)",
      "outgoing_rate (Currency)",
      "valuation_rate (Currency)",
      "stock_value (Currency)",
      "stock_value_difference (Currency)",
      "stock_queue (Long Text)",
      "company (Link)",
      "stock_uom (Link)",
      "project (Link)",
      "fiscal_year (Data)",
      "has_batch_no (Check)",
      "has_serial_no (Check)",
      "is_cancelled (Check)",
      "to_rename (Check)",
      "serial_no (Long Text)",
      "batch_no (Data)",
      "name (Data)",
      "creation (Datetime)",
      "modified (Datetime)",
      "owner (Link)",
      "modified_by (Link)",
      "docstatus (Int)",
      "idx (Int)"
    ]
  },
  "Purchase Order": {
    "module": "Buying",
    "description": "Standard ERPNext doctype for Purchase Order",
    "fields": [
      "title (Data)",
      "naming_series (Select)",
      "supplier (Link)",
      "supplier_name (Data)",
      "order_confirmation_no (Data)",
      "order_confirmation_date (Date)",
      "get_items_from_open_material_requests (Button)",
      "transaction_date (Date)",
      "schedule_date (Date)",
      "company (Link)",
      "apply_tds (Check)",
      "tax_withholding_category (Link)",
      "is_subcontracted (Check)",
      "supplier_warehouse (Link)",
      "amended_from (Link)",
      "cost_center (Link)",
      "project (Link)",
      "currency (Link)",
      "conversion_rate (Float)",
      "buying_price_list (Link)",
      "price_list_currency (Link)",
      "plc_conversion_rate (Float)",
      "ignore_pricing_rule (Check)",
      "scan_barcode (Data)",
      "set_from_warehouse (Link)",
      "set_warehouse (Link)",
      "items (Table)",
      "total_qty (Float)",
      "total_net_weight (Float)",
      "base_total (Currency)",
      "base_net_total (Currency)",
      "total (Currency)",
      "net_total (Currency)",
      "tax_withholding_net_total (Currency)",
      "base_tax_withholding_net_total (Currency)",
      "pricing_rules (Table)",
      "set_reserve_warehouse (Link)",
      "supplied_items (Table)",
      "tax_category (Link)",
      "taxes_and_charges (Link)",
      "shipping_rule (Link)",
      "incoterm (Link)",
      "named_place (Data)",
      "taxes (Table)",
      "base_taxes_and_charges_added (Currency)",
      "base_taxes_and_charges_deducted (Currency)",
      "base_total_taxes_and_charges (Currency)",
      "taxes_and_charges_added (Currency)",
      "taxes_and_charges_deducted (Currency)",
      "total_taxes_and_charges (Currency)",
      "base_grand_total (Currency)",
      "base_rounding_adjustment (Currency)",
      "base_in_words (Data)",
      "base_rounded_total (Currency)",
      "grand_total (Currency)",
      "rounding_adjustment (Currency)",
      "rounded_total (Currency)",
      "disable_rounded_total (Check)",
      "in_words (Data)",
      "advance_paid (Currency)",
      "apply_discount_on (Select)",
      "base_discount_amount (Currency)",
      "additional_discount_percentage (Float)",
      "discount_amount (Currency)",
      "other_charges_calculation (Text Editor)",
      "supplier_address (Link)",
      "address_display (Small Text)",
      "contact_person (Link)",
      "contact_display (Small Text)",
      "contact_mobile (Small Text)",
      "contact_email (Small Text)",
      "shipping_address (Link)",
      "shipping_address_display (Small Text)",
      "billing_address (Link)",
      "billing_address_display (Small Text)",
      "customer (Link)",
      "customer_name (Data)",
      "customer_contact_person (Link)",
      "customer_contact_display (Small Text)",
      "customer_contact_mobile (Small Text)",
      "customer_contact_email (Code)",
      "payment_terms_template (Link)",
      "payment_schedule (Table)",
      "tc_name (Link)",
      "terms (Text Editor)",
      "status (Select)",
      "per_billed (Percent)",
      "per_received (Percent)",
      "letter_head (Link)",
      "group_same_items (Check)",
      "select_print_heading (Link)",
      "language (Data)",
      "from_date (Date)",
      "to_date (Date)",
      "auto_repeat (Link)",
      "update_auto_repeat_reference (Button)",
      "is_internal_supplier (Check)",
      "represents_company (Link)",
      "ref_sq (Link)",
      "party_account_currency (Link)",
      "inter_company_order_reference (Link)",
      "is_old_subcontracting_flow (Check)",
      "name (Data)",
      "creation (Datetime)",
      "modified (Datetime)",
      "owner (Link)",
      "modified_by (Link)",
      "docstatus (Int)",
      "idx (Int)"
    ]
  },
  "Purchase Receipt": {
    "module": "Stock",
    "description": "Standard ERPNext doctype for Purchase Receipt",
    "fields": [
      "title (Data)",
      "naming_series (Select)",
      "supplier (Link)",
      "supplier_name (Data)",
      "supplier_delivery_note (Data)",
      "subcontracting_receipt (Link)",
      "posting_date (Date)",
      "posting_time (Time)",
      "set_posting_time (Check)",
      "company (Link)",
      "apply_putaway_rule (Check)",
      "is_return (Check)",
      "return_against (Link)",
      "cost_center (Link)",
      "project (Link)",
      "currency (Link)",
      "conversion_rate (Float)",
      "buying_price_list (Link)",
      "price_list_currency (Link)",
      "plc_conversion_rate (Float)",
      "ignore_pricing_rule (Check)",
      "scan_barcode (Data)",
      "set_warehouse (Link)",
      "set_from_warehouse (Link)",
      "rejected_warehouse (Link)",
      "is_subcontracted (Check)",
      "supplier_warehouse (Link)",
      "items (Table)",
      "total_qty (Float)",
      "total_net_weight (Float)",
      "base_total (Currency)",
      "base_net_total (Currency)",
      "total (Currency)",
      "net_total (Currency)",
      "tax_withholding_net_total (Currency)",
      "base_tax_withholding_net_total (Currency)",
      "tax_category (Link)",
      "taxes_and_charges (Link)",
      "shipping_rule (Link)",
      "incoterm (Link)",
      "named_place (Data)",
      "taxes (Table)",
      "base_taxes_and_charges_added (Currency)",
      "base_taxes_and_charges_deducted (Currency)",
      "base_total_taxes_and_charges (Currency)",
      "taxes_and_charges_added (Currency)",
      "taxes_and_charges_deducted (Currency)",
      "total_taxes_and_charges (Currency)",
      "base_grand_total (Currency)",
      "base_rounding_adjustment (Currency)",
      "base_rounded_total (Currency)",
      "base_in_words (Data)",
      "grand_total (Currency)",
      "rounding_adjustment (Currency)",
      "rounded_total (Currency)",
      "in_words (Data)",
      "disable_rounded_total (Check)",
      "apply_discount_on (Select)",
      "base_discount_amount (Currency)",
      "additional_discount_percentage (Float)",
      "discount_amount (Currency)",
      "other_charges_calculation (Text Editor)",
      "pricing_rules (Table)",
      "get_current_stock (Button)",
      "supplied_items (Table)",
      "supplier_address (Link)",
      "address_display (Small Text)",
      "contact_person (Link)",
      "contact_display (Small Text)",
      "contact_mobile (Small Text)",
      "contact_email (Small Text)",
      "shipping_address (Link)",
      "shipping_address_display (Small Text)",
      "billing_address (Link)",
      "billing_address_display (Small Text)",
      "tc_name (Link)",
      "terms (Text Editor)",
      "status (Select)",
      "per_billed (Percent)",
      "per_returned (Percent)",
      "auto_repeat (Link)",
      "letter_head (Link)",
      "group_same_items (Check)",
      "select_print_heading (Link)",
      "language (Data)",
      "transporter_name (Data)",
      "lr_no (Data)",
      "lr_date (Date)",
      "instructions (Small Text)",
      "is_internal_supplier (Check)",
      "represents_company (Link)",
      "inter_company_reference (Link)",
      "remarks (Small Text)",
      "range (Data)",
      "amended_from (Link)",
      "is_old_subcontracting_flow (Check)",
      "other_details (HTML)",
      "name (Data)",
      "creation (Datetime)",
      "modified (Datetime)",
      "owner (Link)",
      "modified_by (Link)",
      "docstatus (Int)",
      "idx (Int)"
    ]
  },
  "Supplier": {
    "module": "Buying",
    "description": "Supplier of Goods or Services.",
    "fields": [
      "naming_series (Select)",
      "supplier_name (Data)",
      "country (Link)",
      "supplier_group (Link)",
      "supplier_type (Select)",
      "is_transporter (Check)",
      "image (Attach Image)",
      "default_currency (Link)",
      "default_bank_account (Link)",
      "default_price_list (Link)",
      "is_internal_supplier (Check)",
      "represents_company (Link)",
      "companies (Table)",
      "supplier_details (Text)",
      "website (Data)",
      "language (Link)",
      "tax_id (Data)",
      "tax_category (Link)",
      "tax_withholding_category (Link)",
      "address_html (HTML)",
      "contact_html (HTML)",
      "supplier_primary_address (Link)",
      "primary_address (Text)",
      "supplier_primary_contact (Link)",
      "mobile_no (Read Only)",
      "email_id (Read Only)",
      "payment_terms (Link)",
      "accounts (Table)",
      "allow_purchase_invoice_creation_without_purchase_order (Check)",
      "allow_purchase_invoice_creation_without_purchase_receipt (Check)",
      "is_frozen (Check)",
      "disabled (Check)",
      "warn_rfqs (Check)",
      "warn_pos (Check)",
      "prevent_rfqs (Check)",
      "prevent_pos (Check)",
      "on_hold (Check)",
      "hold_type (Select)",
      "release_date (Date)",
      "portal_users (Table)",
      "name (Data)",
      "creation (Datetime)",
      "modified (Datetime)",
      "owner (Link)",
      "modified_by (Link)",
      "docstatus (Int)",
      "idx (Int)"
    ]
  },
  "Supplier Quotation": {
    "module": "Buying",
    "description": "Standard ERPNext doctype for Supplier Quotation",
    "fields": [
      "title (Data)",
      "naming_series (Select)",
      "supplier (Link)",
      "supplier_name (Data)",
      "company (Link)",
      "status (Select)",
      "transaction_date (Date)",
      "valid_till (Date)",
      "quotation_number (Data)",
      "amended_from (Link)",
      "cost_center (Link)",
      "project (Link)",
      "currency (Link)",
      "conversion_rate (Float)",
      "buying_price_list (Link)",
      "price_list_currency (Link)",
      "plc_conversion_rate (Float)",
      "ignore_pricing_rule (Check)",
      "items (Table)",
      "total_qty (Float)",
      "total_net_weight (Float)",
      "base_total (Currency)",
      "base_net_total (Currency)",
      "total (Currency)",
      "net_total (Currency)",
      "tax_category (Link)",
      "taxes_and_charges (Link)",
      "shipping_rule (Link)",
      "incoterm (Link)",
      "named_place (Data)",
      "taxes (Table)",
      "base_taxes_and_charges_added (Currency)",
      "base_taxes_and_charges_deducted (Currency)",
      "base_total_taxes_and_charges (Currency)",
      "taxes_and_charges_added (Currency)",
      "taxes_and_charges_deducted (Currency)",
      "total_taxes_and_charges (Currency)",
      "apply_discount_on (Select)",
      "base_discount_amount (Currency)",
      "additional_discount_percentage (Float)",
      "discount_amount (Currency)",
      "base_grand_total (Currency)",
      "base_rounding_adjustment (Currency)",
      "base_rounded_total (Currency)",
      "base_in_words (Data)",
      "grand_total (Currency)",
      "rounding_adjustment (Currency)",
      "rounded_total (Currency)",
      "in_words (Data)",
      "disable_rounded_total (Check)",
      "other_charges_calculation (Text Editor)",
      "pricing_rules (Table)",
      "supplier_address (Link)",
      "address_display (Small Text)",
      "contact_person (Link)",
      "contact_display (Small Text)",
      "contact_mobile (Small Text)",
      "contact_email (Data)",
      "shipping_address (Link)",
      "shipping_address_display (Small Text)",
      "billing_address (Link)",
      "billing_address_display (Small Text)",
      "tc_name (Link)",
      "terms (Text Editor)",
      "letter_head (Link)",
      "group_same_items (Check)",
      "select_print_heading (Link)",
      "language (Data)",
      "auto_repeat (Link)",
      "update_auto_repeat_reference (Button)",
      "is_subcontracted (Check)",
      "opportunity (Link)",
      "name (Data)",
      "creation (Datetime)",
      "modified (Datetime)",
      "owner (Link)",
      "modified_by (Link)",
      "docstatus (Int)",
      "idx (Int)"
    ]
  },

  "BOM": {
    "module": "Manufacturing",
    "description": "Standard ERPNext doctype for BOM",
    "fields": [
      "item (Link)",
      "company (Link)",
      "uom (Link)",
      "quantity (Float)",
      "is_active (Check)",
      "is_default (Check)",
      "allow_alternative_item (Check)",
      "set_rate_of_sub_assembly_item_based_on_bom (Check)",
      "project (Link)",
      "image (Attach Image)",
      "rm_cost_as_per (Select)",
      "buying_price_list (Link)",
      "price_list_currency (Link)",
      "plc_conversion_rate (Float)",
      "currency (Link)",
      "conversion_rate (Float)",
      "items (Table)",
      "with_operations (Check)",
      "transfer_material_against (Select)",
      "routing (Link)",
      "fg_based_operating_cost (Check)",
      "operating_cost_per_bom_quantity (Currency)",
      "operations (Table)",
      "scrap_items (Table)",
      "process_loss_percentage (Percent)",
      "process_loss_qty (Float)",
      "operating_cost (Currency)",
      "raw_material_cost (Currency)",
      "scrap_material_cost (Currency)",
      "base_operating_cost (Currency)",
      "base_raw_material_cost (Currency)",
      "base_scrap_material_cost (Currency)",
      "total_cost (Currency)",
      "base_total_cost (Currency)",
      "item_name (Data)",
      "description (Small Text)",
      "has_variants (Check)",
      "inspection_required (Check)",
      "quality_inspection_template (Link)",
      "exploded_items (Table)",
      "show_in_website (Check)",
      "route (Small Text)",
      "website_image (Attach Image)",
      "thumbnail (Data)",
      "show_items (Check)",
      "show_operations (Check)",
      "web_long_description (Text Editor)",
      "bom_creator (Link)",
      "bom_creator_item (Data)",
      "amended_from (Link)",
      "name (Data)",
      "creation (Datetime)",
      "modified (Datetime)",
      "owner (Link)",
      "modified_by (Link)",
      "docstatus (Int)",
      "idx (Int)"
    ]
  },
  "Job Card": {
    "module": "Manufacturing",
    "description": "Standard ERPNext doctype for Job Card",
    "fields": [
      "naming_series (Select)",
      "work_order (Link)",
      "bom_no (Link)",
      "production_item (Link)",
      "employee (Table MultiSelect)",
      "posting_date (Date)",
      "company (Link)",
      "for_quantity (Float)",
      "total_completed_qty (Float)",
      "process_loss_qty (Float)",
      "expected_start_date (Datetime)",
      "time_required (Float)",
      "expected_end_date (Datetime)",
      "scheduled_time_logs (Table)",
      "time_logs (Table)",
      "actual_start_date (Datetime)",
      "total_time_in_mins (Float)",
      "actual_end_date (Datetime)",
      "operation (Link)",
      "wip_warehouse (Link)",
      "workstation_type (Link)",
      "workstation (Link)",
      "quality_inspection_template (Link)",
      "quality_inspection (Link)",
      "sub_operations (Table)",
      "items (Table)",
      "scrap_items (Table)",
      "for_job_card (Link)",
      "is_corrective_job_card (Check)",
      "hour_rate (Currency)",
      "for_operation (Link)",
      "project (Link)",
      "item_name (Read Only)",
      "transferred_qty (Float)",
      "requested_qty (Float)",
      "status (Select)",
      "operation_row_number (Select)",
      "operation_id (Data)",
      "sequence_id (Int)",
      "remarks (Small Text)",
      "serial_and_batch_bundle (Link)",
      "batch_no (Link)",
      "serial_no (Small Text)",
      "barcode (Barcode)",
      "job_started (Check)",
      "started_time (Datetime)",
      "current_time (Int)",
      "amended_from (Link)",
      "name (Data)",
      "creation (Datetime)",
      "modified (Datetime)",
      "owner (Link)",
      "modified_by (Link)",
      "docstatus (Int)",
      "idx (Int)"
    ]
  },
  "Production Plan": {
    "module": "Manufacturing",
    "description": "Standard ERPNext doctype for Production Plan",
    "fields": [
      "naming_series (Select)",
      "company (Link)",
      "get_items_from (Select)",
      "posting_date (Date)",
      "item_code (Link)",
      "customer (Link)",
      "warehouse (Link)",
      "project (Link)",
      "sales_order_status (Select)",
      "from_date (Date)",
      "to_date (Date)",
      "from_delivery_date (Date)",
      "to_delivery_date (Date)",
      "get_sales_orders (Button)",
      "sales_orders (Table)",
      "get_material_request (Button)",
      "material_requests (Table)",
      "get_items (Button)",
      "combine_items (Check)",
      "po_items (Table)",
      "prod_plan_references (Table)",
      "combine_sub_items (Check)",
      "sub_assembly_warehouse (Link)",
      "skip_available_sub_assembly_item (Check)",
      "get_sub_assembly_items (Button)",
      "sub_assembly_items (Table)",
      "download_materials_required (Button)",
      "include_non_stock_items (Check)",
      "include_subcontracted_items (Check)",
      "consider_minimum_order_qty (Check)",
      "include_safety_stock (Check)",
      "ignore_existing_ordered_qty (Check)",
      "for_warehouse (Link)",
      "get_items_for_mr (Button)",
      "transfer_materials (Button)",
      "mr_items (Table)",
      "total_planned_qty (Float)",
      "total_produced_qty (Float)",
      "status (Select)",
      "warehouses (Table MultiSelect)",
      "amended_from (Link)",
      "name (Data)",
      "creation (Datetime)",
      "modified (Datetime)",
      "owner (Link)",
      "modified_by (Link)",
      "docstatus (Int)",
      "idx (Int)"
    ]
  },
  "Operation": {
    "module": "Manufacturing",
    "description": "Standard ERPNext doctype for Operation",
    "fields": [
      "workstation (Link)",
      "is_corrective_operation (Check)",
      "create_job_card_based_on_batch_size (Check)",
      "quality_inspection_template (Link)",
      "batch_size (Int)",
      "sub_operations (Table)",
      "total_operation_time (Float)",
      "description (Text)",
      "name (Data)",
      "creation (Datetime)",
      "modified (Datetime)",
      "owner (Link)",
      "modified_by (Link)",
      "docstatus (Int)",
      "idx (Int)"
    ]
  },
  "Routing": {
    "module": "Manufacturing",
    "description": "Standard ERPNext doctype for Routing",
    "fields": [
      "routing_name (Data)",
      "disabled (Check)",
      "operations (Table)",
      "name (Data)",
      "creation (Datetime)",
      "modified (Datetime)",
      "owner (Link)",
      "modified_by (Link)",
      "docstatus (Int)",
      "idx (Int)"
    ]
  },
  "Employee": {
    "module": "Setup",
    "description": "Standard ERPNext doctype for Employee",
    "fields": [
      "employee (Data)",
      "naming_series (Select)",
      "first_name (Data)",
      "middle_name (Data)",
      "last_name (Data)",
      "employee_name (Data)",
      "gender (Link)",
      "date_of_birth (Date)",
      "salutation (Link)",
      "date_of_joining (Date)",
      "image (Attach Image)",
      "status (Select)",
      "user_id (Link)",
      "create_user (Button)",
      "create_user_permission (Check)",
      "company (Link)",
      "department (Link)",
      "employee_number (Data)",
      "designation (Link)",
      "reports_to (Link)",
      "branch (Link)",
      "scheduled_confirmation_date (Date)",
      "final_confirmation_date (Date)",
      "contract_end_date (Date)",
      "notice_number_of_days (Int)",
      "date_of_retirement (Date)",
      "cell_number (Data)",
      "personal_email (Data)",
      "company_email (Data)",
      "prefered_contact_email (Select)",
      "prefered_email (Data)",
      "unsubscribed (Check)",
      "current_address (Small Text)",
      "current_accommodation_type (Select)",
      "permanent_address (Small Text)",
      "permanent_accommodation_type (Select)",
      "person_to_be_contacted (Data)",
      "emergency_phone_number (Data)",
      "relation (Data)",
      "attendance_device_id (Data)",
      "holiday_list (Link)",
      "ctc (Currency)",
      "salary_currency (Link)",
      "salary_mode (Select)",
      "bank_name (Data)",
      "bank_ac_no (Data)",
      "iban (Data)",
      "marital_status (Select)",
      "family_background (Small Text)",
      "blood_group (Select)",
      "health_details (Small Text)",
      "passport_number (Data)",
      "valid_upto (Date)",
      "date_of_issue (Date)",
      "place_of_issue (Data)",
      "bio (Text Editor)",
      "education (Table)",
      "external_work_history (Table)",
      "internal_work_history (Table)",
      "resignation_letter_date (Date)",
      "relieving_date (Date)",
      "held_on (Date)",
      "new_workplace (Data)",
      "leave_encashed (Select)",
      "encashment_date (Date)",
      "reason_for_leaving (Small Text)",
      "feedback (Small Text)",
      "lft (Int)",
      "rgt (Int)",
      "old_parent (Data)",
      "name (Data)",
      "creation (Datetime)",
      "modified (Datetime)",
      "owner (Link)",
      "modified_by (Link)",
      "docstatus (Int)",
      "idx (Int)"
    ]
  },
  "Department": {
    "module": "Setup",
    "description": "Standard ERPNext doctype for Department",
    "fields": [
      "department_name (Data)",
      "parent_department (Link)",
      "company (Link)",
      "is_group (Check)",
      "disabled (Check)",
      "lft (Int)",
      "rgt (Int)",
      "old_parent (Data)",
      "name (Data)",
      "creation (Datetime)",
      "modified (Datetime)",
      "owner (Link)",
      "modified_by (Link)",
      "docstatus (Int)",
      "idx (Int)"
    ]
  },
  "Designation": {
    "module": "Setup",
    "description": "Standard ERPNext doctype for Designation",
    "fields": [
      "designation_name (Data)",
      "description (Text)",
      "name (Data)",
      "creation (Datetime)",
      "modified (Datetime)",
      "owner (Link)",
      "modified_by (Link)",
      "docstatus (Int)",
      "idx (Int)"
    ]
  },
  "Payment Entry": {
    "module": "Accounts",
    "description": "Standard ERPNext doctype for Payment Entry",
    "fields": [
      "naming_series (Select)",
      "payment_type (Select)",
      "payment_order_status (Select)",
      "posting_date (Date)",
      "company (Link)",
      "mode_of_payment (Link)",
      "party_type (Link)",
      "party (Dynamic Link)",
      "party_name (Data)",
      "book_advance_payments_in_separate_party_account (Check)",
      "reconcile_on_advance_payment_date (Check)",
      "advance_reconciliation_takes_effect_on (Select)",
      "bank_account (Link)",
      "party_bank_account (Link)",
      "contact_person (Link)",
      "contact_email (Data)",
      "party_balance (Currency)",
      "paid_from (Link)",
      "paid_from_account_type (Data)",
      "paid_from_account_currency (Link)",
      "paid_from_account_balance (Currency)",
      "paid_to (Link)",
      "paid_to_account_type (Data)",
      "paid_to_account_currency (Link)",
      "paid_to_account_balance (Currency)",
      "paid_amount (Currency)",
      "paid_amount_after_tax (Currency)",
      "source_exchange_rate (Float)",
      "base_paid_amount (Currency)",
      "base_paid_amount_after_tax (Currency)",
      "received_amount (Currency)",
      "received_amount_after_tax (Currency)",
      "target_exchange_rate (Float)",
      "base_received_amount (Currency)",
      "base_received_amount_after_tax (Currency)",
      "get_outstanding_invoices (Button)",
      "get_outstanding_orders (Button)",
      "references (Table)",
      "total_allocated_amount (Currency)",
      "base_total_allocated_amount (Currency)",
      "unallocated_amount (Currency)",
      "difference_amount (Currency)",
      "write_off_difference_amount (Button)",
      "purchase_taxes_and_charges_template (Link)",
      "sales_taxes_and_charges_template (Link)",
      "apply_tax_withholding_amount (Check)",
      "tax_withholding_category (Link)",
      "taxes (Table)",
      "base_total_taxes_and_charges (Currency)",
      "total_taxes_and_charges (Currency)",
      "deductions (Table)",
      "reference_no (Data)",
      "reference_date (Date)",
      "clearance_date (Date)",
      "project (Link)",
      "cost_center (Link)",
      "status (Select)",
      "custom_remarks (Check)",
      "remarks (Small Text)",
      "base_in_words (Small Text)",
      "is_opening (Select)",
      "letter_head (Link)",
      "print_heading (Link)",
      "bank (Read Only)",
      "bank_account_no (Read Only)",
      "payment_order (Link)",
      "in_words (Small Text)",
      "auto_repeat (Link)",
      "amended_from (Link)",
      "title (Data)",
      "name (Data)",
      "creation (Datetime)",
      "modified (Datetime)",
      "owner (Link)",
      "modified_by (Link)",
      "docstatus (Int)",
      "idx (Int)"
    ]
  },
  "Journal Entry": {
    "module": "Accounts",
    "description": "Standard ERPNext doctype for Journal Entry",
    "fields": [
      "is_system_generated (Check)",
      "title (Data)",
      "voucher_type (Select)",
      "naming_series (Select)",
      "finance_book (Link)",
      "process_deferred_accounting (Link)",
      "reversal_of (Link)",
      "tax_withholding_category (Link)",
      "from_template (Link)",
      "company (Link)",
      "posting_date (Date)",
      "apply_tds (Check)",
      "accounts (Table)",
      "cheque_no (Data)",
      "cheque_date (Date)",
      "user_remark (Small Text)",
      "total_debit (Currency)",
      "total_credit (Currency)",
      "difference (Currency)",
      "get_balance (Button)",
      "multi_currency (Check)",
      "total_amount_currency (Link)",
      "total_amount (Currency)",
      "total_amount_in_words (Data)",
      "clearance_date (Date)",
      "remark (Small Text)",
      "paid_loan (Data)",
      "inter_company_journal_entry_reference (Link)",
      "bill_no (Data)",
      "bill_date (Date)",
      "due_date (Date)",
      "write_off_based_on (Select)",
      "get_outstanding_invoices (Button)",
      "write_off_amount (Currency)",
      "pay_to_recd_from (Data)",
      "letter_head (Link)",
      "select_print_heading (Link)",
      "mode_of_payment (Link)",
      "payment_order (Link)",
      "is_opening (Select)",
      "stock_entry (Link)",
      "auto_repeat (Link)",
      "amended_from (Link)",
      "name (Data)",
      "creation (Datetime)",
      "modified (Datetime)",
      "owner (Link)",
      "modified_by (Link)",
      "docstatus (Int)",
      "idx (Int)"
    ]
  },
  "Account": {
    "module": "Accounts",
    "description": "Heads (or groups) against which Accounting Entries are made and balances are maintained.",
    "fields": [
      "disabled (Check)",
      "account_name (Data)",
      "account_number (Data)",
      "is_group (Check)",
      "company (Link)",
      "root_type (Select)",
      "report_type (Select)",
      "account_currency (Link)",
      "parent_account (Link)",
      "account_type (Select)",
      "tax_rate (Float)",
      "freeze_account (Select)",
      "balance_must_be (Select)",
      "lft (Int)",
      "rgt (Int)",
      "old_parent (Data)",
      "include_in_gross (Check)",
      "name (Data)",
      "creation (Datetime)",
      "modified (Datetime)",
      "owner (Link)",
      "modified_by (Link)",
      "docstatus (Int)",
      "idx (Int)"
    ]
  },
  "Cost Center": {
    "module": "Accounts",
    "description": "Track separate Income and Expense for product verticals or divisions.",
    "fields": [
      "cost_center_name (Data)",
      "cost_center_number (Data)",
      "parent_cost_center (Link)",
      "company (Link)",
      "is_group (Check)",
      "disabled (Check)",
      "lft (Int)",
      "rgt (Int)",
      "old_parent (Link)",
      "name (Data)",
      "creation (Datetime)",
      "modified (Datetime)",
      "owner (Link)",
      "modified_by (Link)",
      "docstatus (Int)",
      "idx (Int)"
    ]
  },
  "Tax Category": {
    "module": "Accounts",
    "description": "Standard ERPNext doctype for Tax Category",
    "fields": [
      "title (Data)",
      "disabled (Check)",
      "name (Data)",
      "creation (Datetime)",
      "modified (Datetime)",
      "owner (Link)",
      "modified_by (Link)",
      "docstatus (Int)",
      "idx (Int)"
    ]
  },
  "Company": {
    "module": "Setup",
    "description": "Legal Entity / Subsidiary with a separate Chart of Accounts belonging to the Organization.",
    "fields": [
      "company_name (Data)",
      "abbr (Data)",
      "default_currency (Link)",
      "country (Link)",
      "is_group (Check)",
      "default_holiday_list (Link)",
      "default_letter_head (Link)",
      "tax_id (Data)",
      "domain (Data)",
      "date_of_establishment (Date)",
      "parent_company (Link)",
      "company_logo (Attach Image)",
      "date_of_incorporation (Date)",
      "phone_no (Data)",
      "email (Data)",
      "company_description (Text Editor)",
      "date_of_commencement (Date)",
      "fax (Data)",
      "website (Data)",
      "address_html (HTML)",
      "registration_details (Code)",
      "lft (Int)",
      "rgt (Int)",
      "old_parent (Data)",
      "create_chart_of_accounts_based_on (Select)",
      "existing_company (Link)",
      "chart_of_accounts (Select)",
      "default_bank_account (Link)",
      "default_cash_account (Link)",
      "default_receivable_account (Link)",
      "default_payable_account (Link)",
      "write_off_account (Link)",
      "unrealized_profit_loss_account (Link)",
      "allow_account_creation_against_child_company (Check)",
      "default_expense_account (Link)",
      "default_income_account (Link)",
      "default_discount_account (Link)",
      "payment_terms (Link)",
      "cost_center (Link)",
      "default_finance_book (Link)",
      "exchange_gain_loss_account (Link)",
      "unrealized_exchange_gain_loss_account (Link)",
      "round_off_account (Link)",
      "round_off_cost_center (Link)",
      "round_off_for_opening (Link)",
      "default_deferred_revenue_account (Link)",
      "default_deferred_expense_account (Link)",
      "book_advance_payments_in_separate_party_account (Check)",
      "reconcile_on_advance_payment_date (Check)",
      "reconciliation_takes_effect_on (Select)",
      "default_advance_received_account (Link)",
      "default_advance_paid_account (Link)",
      "auto_exchange_rate_revaluation (Check)",
      "auto_err_frequency (Select)",
      "submit_err_jv (Check)",
      "exception_budget_approver_role (Link)",
      "accumulated_depreciation_account (Link)",
      "depreciation_expense_account (Link)",
      "series_for_depreciation_entry (Data)",
      "expenses_included_in_asset_valuation (Link)",
      "disposal_account (Link)",
      "depreciation_cost_center (Link)",
      "capital_work_in_progress_account (Link)",
      "asset_received_but_not_billed (Link)",
      "default_buying_terms (Link)",
      "sales_monthly_history (Small Text)",
      "monthly_sales_target (Currency)",
      "total_monthly_sales (Currency)",
      "default_selling_terms (Link)",
      "default_warehouse_for_sales_return (Link)",
      "credit_limit (Currency)",
      "transactions_annual_history (Code)",
      "enable_perpetual_inventory (Check)",
      "enable_provisional_accounting_for_non_stock_items (Check)",
      "default_inventory_account (Link)",
      "stock_adjustment_account (Link)",
      "default_in_transit_warehouse (Link)",
      "stock_received_but_not_billed (Link)",
      "default_provisional_account (Link)",
      "expenses_included_in_valuation (Link)",
      "default_operating_cost_account (Link)",
      "name (Data)",
      "creation (Datetime)",
      "modified (Datetime)",
      "owner (Link)",
      "modified_by (Link)",
      "docstatus (Int)",
      "idx (Int)"
    ]
  },
  "Mode of Payment": {
    "module": "Accounts",
    "description": "Standard ERPNext doctype for Mode of Payment",
    "fields": [
      "mode_of_payment (Data)",
      "enabled (Check)",
      "type (Select)",
      "accounts (Table)",
      "name (Data)",
      "creation (Datetime)",
      "modified (Datetime)",
      "owner (Link)",
      "modified_by (Link)",
      "docstatus (Int)",
      "idx (Int)"
    ]
  },
  "Lead": {
    "module": "CRM",
    "description": "Standard ERPNext doctype for Lead",
    "fields": [
      "naming_series (Select)",
      "salutation (Link)",
      "first_name (Data)",
      "middle_name (Data)",
      "last_name (Data)",
      "lead_name (Data)",
      "job_title (Data)",
      "gender (Link)",
      "source (Link)",
      "lead_owner (Link)",
      "status (Select)",
      "customer (Link)",
      "type (Select)",
      "request_type (Select)",
      "email_id (Data)",
      "website (Data)",
      "mobile_no (Data)",
      "whatsapp_no (Data)",
      "phone (Data)",
      "phone_ext (Data)",
      "company_name (Data)",
      "no_of_employees (Select)",
      "annual_revenue (Currency)",
      "industry (Link)",
      "market_segment (Link)",
      "territory (Link)",
      "fax (Data)",
      "address_html (HTML)",
      "city (Data)",
      "state (Data)",
      "country (Link)",
      "contact_html (HTML)",
      "qualification_status (Select)",
      "qualified_by (Link)",
      "qualified_on (Date)",
      "campaign_name (Link)",
      "company (Link)",
      "language (Link)",
      "image (Attach Image)",
      "title (Data)",
      "disabled (Check)",
      "unsubscribed (Check)",
      "blog_subscriber (Check)",
      "open_activities_html (HTML)",
      "all_activities_html (HTML)",
      "notes_html (HTML)",
      "notes (Table)",
      "name (Data)",
      "creation (Datetime)",
      "modified (Datetime)",
      "owner (Link)",
      "modified_by (Link)",
      "docstatus (Int)",
      "idx (Int)"
    ]
  },
  "Opportunity": {
    "module": "CRM",
    "description": "Potential Sales Deal",
    "fields": [
      "naming_series (Select)",
      "opportunity_from (Link)",
      "party_name (Dynamic Link)",
      "customer_name (Data)",
      "status (Select)",
      "opportunity_type (Link)",
      "source (Link)",
      "opportunity_owner (Link)",
      "sales_stage (Link)",
      "expected_closing (Date)",
      "probability (Percent)",
      "no_of_employees (Select)",
      "annual_revenue (Currency)",
      "customer_group (Link)",
      "industry (Link)",
      "market_segment (Link)",
      "website (Data)",
      "city (Data)",
      "state (Data)",
      "country (Link)",
      "territory (Link)",
      "currency (Link)",
      "conversion_rate (Float)",
      "opportunity_amount (Currency)",
      "base_opportunity_amount (Currency)",
      "company (Link)",
      "campaign (Link)",
      "transaction_date (Date)",
      "language (Link)",
      "amended_from (Link)",
      "title (Data)",
      "first_response_time (Duration)",
      "lost_reasons (Table MultiSelect)",
      "order_lost_reason (Small Text)",
      "competitors (Table MultiSelect)",
      "contact_person (Link)",
      "job_title (Data)",
      "contact_email (Data)",
      "contact_mobile (Data)",
      "whatsapp (Data)",
      "phone (Data)",
      "phone_ext (Data)",
      "address_html (HTML)",
      "customer_address (Link)",
      "address_display (Small Text)",
      "contact_html (HTML)",
      "contact_display (Small Text)",
      "items (Table)",
      "base_total (Currency)",
      "total (Currency)",
      "open_activities_html (HTML)",
      "all_activities_html (HTML)",
      "notes_html (HTML)",
      "notes (Table)",
      "name (Data)",
      "creation (Datetime)",
      "modified (Datetime)",
      "owner (Link)",
      "modified_by (Link)",
      "docstatus (Int)",
      "idx (Int)"
    ]
  },
  "Issue": {
    "module": "Support",
    "description": "Standard ERPNext doctype for Issue",
    "fields": [
      "naming_series (Select)",
      "subject (Data)",
      "customer (Link)",
      "raised_by (Data)",
      "status (Select)",
      "priority (Link)",
      "issue_type (Link)",
      "issue_split_from (Link)",
      "description (Text Editor)",
      "service_level_agreement (Link)",
      "response_by (Datetime)",
      "reset_service_level_agreement (Button)",
      "agreement_status (Select)",
      "resolution_by (Datetime)",
      "service_level_agreement_creation (Datetime)",
      "on_hold_since (Datetime)",
      "total_hold_time (Duration)",
      "first_response_time (Duration)",
      "first_responded_on (Datetime)",
      "avg_response_time (Duration)",
      "resolution_details (Text Editor)",
      "opening_date (Date)",
      "opening_time (Time)",
      "resolution_date (Datetime)",
      "resolution_time (Duration)",
      "user_resolution_time (Duration)",
      "lead (Link)",
      "contact (Link)",
      "email_account (Link)",
      "customer_name (Data)",
      "project (Link)",
      "company (Link)",
      "via_customer_portal (Check)",
      "attachment (Attach)",
      "content_type (Data)",
      "name (Data)",
      "creation (Datetime)",
      "modified (Datetime)",
      "owner (Link)",
      "modified_by (Link)",
      "docstatus (Int)",
      "idx (Int)"
    ]
  },
  "Contact": {
    "module": "Contacts",
    "description": "Standard ERPNext doctype for Contact",
    "fields": [
      "first_name (Data)",
      "middle_name (Data)",
      "last_name (Data)",
      "full_name (Data)",
      "email_id (Data)",
      "user (Link)",
      "address (Link)",
      "sync_with_google_contacts (Check)",
      "status (Select)",
      "salutation (Link)",
      "designation (Data)",
      "gender (Link)",
      "phone (Data)",
      "mobile_no (Data)",
      "company_name (Data)",
      "image (Attach Image)",
      "google_contacts (Link)",
      "google_contacts_id (Data)",
      "pulled_from_google_contacts (Check)",
      "email_ids (Table)",
      "phone_nos (Table)",
      "links (Table)",
      "is_primary_contact (Check)",
      "is_billing_contact (Check)",
      "department (Data)",
      "unsubscribed (Check)",
      "name (Data)",
      "creation (Datetime)",
      "modified (Datetime)",
      "owner (Link)",
      "modified_by (Link)",
      "docstatus (Int)",
      "idx (Int)"
    ]
  },
  "Communication": {
    "module": "Core",
    "description": "Keeps track of all communications",
    "fields": [
      "subject (Small Text)",
      "communication_medium (Select)",
      "sender (Data)",
      "recipients (Code)",
      "cc (Code)",
      "bcc (Code)",
      "phone_no (Data)",
      "delivery_status (Select)",
      "content (Text Editor)",
      "text_content (Code)",
      "communication_type (Select)",
      "comment_type (Select)",
      "status (Select)",
      "sent_or_received (Select)",
      "communication_date (Datetime)",
      "read_receipt (Check)",
      "send_after (Datetime)",
      "sender_full_name (Data)",
      "read_by_recipient (Check)",
      "read_by_recipient_on (Datetime)",
      "reference_doctype (Link)",
      "reference_name (Dynamic Link)",
      "reference_owner (Read Only)",
      "email_account (Link)",
      "in_reply_to (Link)",
      "user (Link)",
      "email_template (Link)",
      "unread_notification_sent (Check)",
      "seen (Check)",
      "_user_tags (Data)",
      "timeline_links (Table)",
      "message_id (Small Text)",
      "uid (Int)",
      "imap_folder (Data)",
      "email_status (Select)",
      "has_attachment (Check)",
      "rating (Int)",
      "feedback_request (Data)",
      "name (Data)",
      "creation (Datetime)",
      "modified (Datetime)",
      "owner (Link)",
      "modified_by (Link)",
      "docstatus (Int)",
      "idx (Int)"
    ]
  },
  "Project": {
    "module": "Projects",
    "description": "Standard ERPNext doctype for Project",
    "fields": [
      "naming_series (Select)",
      "project_name (Data)",
      "status (Select)",
      "project_type (Link)",
      "is_active (Select)",
      "percent_complete_method (Select)",
      "percent_complete (Percent)",
      "project_template (Link)",
      "expected_start_date (Date)",
      "expected_end_date (Date)",
      "priority (Select)",
      "department (Link)",
      "customer (Link)",
      "sales_order (Link)",
      "users (Table)",
      "copied_from (Data)",
      "notes (Text Editor)",
      "actual_start_date (Date)",
      "actual_time (Float)",
      "actual_end_date (Date)",
      "estimated_costing (Currency)",
      "total_costing_amount (Currency)",
      "total_purchase_cost (Currency)",
      "company (Link)",
      "total_sales_amount (Currency)",
      "total_billable_amount (Currency)",
      "total_billed_amount (Currency)",
      "total_consumed_material_cost (Currency)",
      "cost_center (Link)",
      "gross_margin (Currency)",
      "per_gross_margin (Percent)",
      "collect_progress (Check)",
      "holiday_list (Link)",
      "frequency (Select)",
      "from_time (Time)",
      "to_time (Time)",
      "first_email (Time)",
      "second_email (Time)",
      "daily_time_to_send (Time)",
      "day_to_send (Select)",
      "weekly_time_to_send (Time)",
      "message (Text)",
      "name (Data)",
      "creation (Datetime)",
      "modified (Datetime)",
      "owner (Link)",
      "modified_by (Link)",
      "docstatus (Int)",
      "idx (Int)"
    ]
  },
  "Task": {
    "module": "Projects",
    "description": "Standard ERPNext doctype for Task",
    "fields": [
      "subject (Data)",
      "project (Link)",
      "issue (Link)",
      "type (Link)",
      "color (Color)",
      "is_group (Check)",
      "is_template (Check)",
      "status (Select)",
      "priority (Select)",
      "task_weight (Float)",
      "parent_task (Link)",
      "completed_by (Link)",
      "completed_on (Date)",
      "exp_start_date (Date)",
      "expected_time (Float)",
      "start (Int)",
      "exp_end_date (Date)",
      "progress (Percent)",
      "duration (Int)",
      "is_milestone (Check)",
      "description (Text Editor)",
      "depends_on (Table)",
      "depends_on_tasks (Code)",
      "act_start_date (Date)",
      "actual_time (Float)",
      "act_end_date (Date)",
      "total_costing_amount (Currency)",
      "total_billing_amount (Currency)",
      "review_date (Date)",
      "closing_date (Date)",
      "department (Link)",
      "company (Link)",
      "lft (Int)",
      "rgt (Int)",
      "old_parent (Data)",
      "template_task (Data)",
      "name (Data)",
      "creation (Datetime)",
      "modified (Datetime)",
      "owner (Link)",
      "modified_by (Link)",
      "docstatus (Int)",
      "idx (Int)"
    ]
  },
  "Timesheet": {
    "module": "Projects",
    "description": "Standard ERPNext doctype for Timesheet",
    "fields": [
      "title (Data)",
      "naming_series (Select)",
      "company (Link)",
      "customer (Link)",
      "currency (Link)",
      "exchange_rate (Float)",
      "sales_invoice (Link)",
      "status (Select)",
      "parent_project (Link)",
      "employee (Link)",
      "employee_name (Data)",
      "department (Link)",
      "user (Link)",
      "start_date (Date)",
      "end_date (Date)",
      "time_logs (Table)",
      "total_hours (Float)",
      "total_billable_hours (Float)",
      "base_total_billable_amount (Currency)",
      "base_total_billed_amount (Currency)",
      "base_total_costing_amount (Currency)",
      "total_billed_hours (Float)",
      "total_billable_amount (Currency)",
      "total_billed_amount (Currency)",
      "total_costing_amount (Currency)",
      "per_billed (Percent)",
      "note (Text Editor)",
      "amended_from (Link)",
      "name (Data)",
      "creation (Datetime)",
      "modified (Datetime)",
      "owner (Link)",
      "modified_by (Link)",
      "docstatus (Int)",
      "idx (Int)"
    ]
  }
}